.gitignore
LICENSE
README.md
setup.py
py_yahoo_prices/__init__.py
py_yahoo_prices/price_fetcher.py
py_yahoo_prices.egg-info/PKG-INFO
py_yahoo_prices.egg-info/SOURCES.txt
py_yahoo_prices.egg-info/dependency_links.txt
py_yahoo_prices.egg-info/requires.txt
py_yahoo_prices.egg-info/top_level.txt