Metadata-Version: 1.0
Name: py-yahoo-prices
Version: 0.5
Summary: Get daily/weekly/monthly prices of equities from yahoo's new tricky endpoint
Home-page: https://github.com/alisiddiq/py_yahoo_prices
Author: Ali Siddiq
Author-email: ali.bin.siddiq@gmail.com
License: MIT
Keywords: stocks,yahoo,prices
Platform: UNKNOWN
